_pyspectrum.cp311-win_amd64.pyd
pyspectrum/__init__.py
pyspectrum/data.py
pyspectrum/device_factory.py
pyspectrum/errors.py
pyspectrum/ethernet_device.py
pyspectrum/spectrometer.py
vmk_spectrum-0.0.10.dist-info/METADATA
vmk_spectrum-0.0.10.dist-info/WHEEL
vmk_spectrum-0.0.10.dist-info/top_level.txt
vmk_spectrum-0.0.10.dist-info/RECORD
