Metadata-Version: 2.1
Name: vmk-spectrum
Version: 0.0.10
Author: leadpogrommer
Requires-Python: >=3.10
Requires-Dist: numpy
Requires-Dist: matplotlib
Requires-Dist: scipy
Provides-Extra: test
Requires-Dist: pytest (>=6.0) ; extra == 'test'
